lcs2/__init__.py
lcs2-2.0.0.dist-info/licenses/LICENSE
lcs2-2.0.0.dist-info/METADATA
lcs2-2.0.0.dist-info/WHEEL
lcs2-2.0.0.dist-info/top_level.txt
lcs2-2.0.0.dist-info/RECORD
