Metadata-Version: 2.4
Name: lcs2
Version: 2.0.0
Summary: Compute the longest or optimal weighted, most contiguous common subsequence and diff for a pair of sequences
Home-page: https://github.com/danmysak/lcs2
Author: Danylo Mysak
Author-email: danmysak@gmail.com
Project-URL: Bug Tracker, https://github.com/danmysak/lcs2/issues
Classifier: Programming Language :: Python :: 3
Classifier: License :: OSI Approved :: MIT License
Classifier: Operating System :: OS Independent
Requires-Python: >=3.12
License-File: LICENSE
Dynamic: license-file
